{
 "creation": "2020-02-07 16:19:44.165672",
 "doctype": "DocType",
 "editable_grid": 1,
 "engine": "InnoDB",
 "field_order": [
  "day",
  "from_time",
  "to_time"
 ],
 "fields": [
  {
   "fieldname": "day",
   "fieldtype": "Link",
   "in_list_view": 1,
   "label": "Day",
   "options": "Week Day",
   "reqd": 1
  },
  {
   "fieldname": "from_time",
   "fieldtype": "Time",
   "in_list_view": 1,
   "label": "From Time",
   "reqd": 1
  },
  {
   "fieldname": "to_time",
   "fieldtype": "Time",
   "in_list_view": 1,
   "label": "To Time",
   "reqd": 1
  }
 ],
 "istable": 1,
 "modified": "2020-02-07 16:19:44.165672",
 "modified_by": "Administrator",
 "module": "Services",
 "name": "Available Time Slot",
 "owner": "Administrator",
 "permissions": [],
 "sort_field": "modified",
 "sort_order": "DESC",
 "track_changes": 1
}